{"error": "OK", "limit": 1, "offset": 0, "number_of_page_results": 1, "number_of_total_results": 1, "status_code": 1, "results": {"aliases": null, "api_detail_url": "https://www.giantbomb.com/api/franchise/3025-1008/", "characters": [{"api_detail_url": "https://www.giantbomb.com/api/character/3005-6944/", "id": 6944, "name": "Bloom", "site_detail_url": "https://www.giantbomb.com/bloom/3005-6944/"}, {"api_detail_url": "https://www.giantbomb.com/api/character/3005-6945/", "id": 6945, "name": "Stella", "site_detail_url": "https://www.giantbomb.com/stella/3005-6945/"}, {"api_detail_url": "https://www.giantbomb.com/api/character/3005-6946/", "id": 6946, "name": "Musa", "site_detail_url": "https://www.giantbomb.com/musa/3005-6946/"}, {"api_detail_url": "https://www.giantbomb.com/api/character/3005-6947/", "id": 6947, "name": "Flora", "site_detail_url": "https://www.giantbomb.com/flora/3005-6947/"}, {"api_detail_url": "https://www.giantbomb.com/api/character/3005-6948/", "id": 6948, "name": "Tecna", "site_detail_url": "https://www.giantbomb.com/tecna/3005-6948/"}, {"api_detail_url": "https://www.giantbomb.com/api/character/3005-6951/", "id": 6951, "name": "Aisha", "site_detail_url": "https://www.giantbomb.com/aisha/3005-6951/"}], "concepts": [{"api_detail_url": "https://www.giantbomb.com/api/concept/3015-765/", "id": 765, "name": "Games Based on Anime", "site_detail_url": "https://www.giantbomb.com/games-based-on-anime/3015-765/"}, {"api_detail_url": "https://www.giantbomb.com/api/concept/3015-653/", "id": 653, "name": "Tie-In", "site_detail_url": "https://www.giantbomb.com/tie-in/3015-653/"}, {"api_detail_url": "https://www.giantbomb.com/api/concept/3015-1754/", "id": 1754, "name": "Adapted from Television", "site_detail_url": "https://www.giantbomb.com/adapted-from-television/3015-1754/"}, {"api_detail_url": "https://www.giantbomb.com/api/concept/3015-1524/", "id": 1524, "name": "Kid Friendly", "site_detail_url": "https://www.giantbomb.com/kid-friendly/3015-1524/"}, {"api_detail_url": "https://www.giantbomb.com/api/concept/3015-1098/", "id": 1098, "name": "Licensed Game", "site_detail_url": "https://www.giantbomb.com/licensed-game/3015-1098/"}, {"api_detail_url": "https://www.giantbomb.com/api/concept/3015-2469/", "id": 2469, "name": "Games for Girls", "site_detail_url": "https://www.giantbomb.com/games-for-girls/3015-2469/"}, {"api_detail_url": "https://www.giantbomb.com/api/concept/3015-2287/", "id": 2287, "name": "Female Protagonists", "site_detail_url": "https://www.giantbomb.com/female-protagonists/3015-2287/"}, {"api_detail_url": "https://www.giantbomb.com/api/concept/3015-350/", "id": 350, "name": "Flight", "site_detail_url": "https://www.giantbomb.com/flight/3015-350/"}, {"api_detail_url": "https://www.giantbomb.com/api/concept/3015-986/", "id": 986, "name": "Xtreme Naming", "site_detail_url": "https://www.giantbomb.com/xtreme-naming/3015-986/"}, {"api_detail_url": "https://www.giantbomb.com/api/concept/3015-3437/", "id": 3437, "name": "E3 2005", "site_detail_url": "https://www.giantbomb.com/e3-2005/3015-3437/"}, {"api_detail_url": "https://www.giantbomb.com/api/concept/3015-3518/", "id": 3518, "name": "Spellcaster", "site_detail_url": "https://www.giantbomb.com/spellcaster/3015-3518/"}, {"api_detail_url": "https://www.giantbomb.com/api/concept/3015-98/", "id": 98, "name": "Magic", "site_detail_url": "https://www.giantbomb.com/magic/3015-98/"}, {"api_detail_url": "https://www.giantbomb.com/api/concept/3015-1798/", "id": 1798, "name": "Superhero", "site_detail_url": "https://www.giantbomb.com/superhero/3015-1798/"}, {"api_detail_url": "https://www.giantbomb.com/api/concept/3015-315/", "id": 315, "name": "Hero Unit", "site_detail_url": "https://www.giantbomb.com/hero-unit/3015-315/"}, {"api_detail_url": "https://www.giantbomb.com/api/concept/3015-3757/", "id": 3757, "name": "Superpowers", "site_detail_url": "https://www.giantbomb.com/superpowers/3015-3757/"}, {"api_detail_url": "https://www.giantbomb.com/api/concept/3015-2721/", "id": 2721, "name": "Fairy", "site_detail_url": "https://www.giantbomb.com/fairy/3015-2721/"}], "date_added": "2008-08-27 19:37:30", "date_last_updated": "2020-11-08 17:12:42", "deck": "Franchise of the popular animated show Winx Club.", "description": "<h2>Overview</h2><figure data-align=\"right\" data-img-src=\"https://static.giantbomb.com/uploads/original/11/110502/2288076-winxwallpaper_1280x1024_group.jpg\" data-ref-id=\"1300-2288076\" data-size=\"small\" data-ratio=\"0.8\" data-width=\"1280\" data-embed-type=\"image\" style=\"width: 1280px\"><a class=\"fluid-height\" style=\"padding-bottom:80.0%\" href=\"https://static.giantbomb.com/uploads/original/11/110502/2288076-winxwallpaper_1280x1024_group.jpg\" data-ref-id=\"1300-2288076\"><img alt=\"Nickelodeon Promo\" src=\"https://www.giantbomb.com/a/uploads/scale_small/11/110502/2288076-winxwallpaper_1280x1024_group.jpg\" srcset=\"https://www.giantbomb.com/a/uploads/original/11/110502/2288076-winxwallpaper_1280x1024_group.jpg 1280w, https://www.giantbomb.com/a/uploads/scale_super/11/110502/2288076-winxwallpaper_1280x1024_group.jpg 960w, https://www.giantbomb.com/a/uploads/scale_medium/11/110502/2288076-winxwallpaper_1280x1024_group.jpg 480w, https://www.giantbomb.com/a/uploads/scale_small/11/110502/2288076-winxwallpaper_1280x1024_group.jpg 320w\" sizes=\"(max-width: 320px) 100vw, 320px\" data-width=\"320\"></a><figcaption>Nickelodeon Promo</figcaption></figure><p>Winx Club is an animated series co-produced by Rainbow SpA and Nickelodeon. It was created by Iginio Straffi. The show is about a group of magical fairies called the Winx Club. Together they face evil witches, wizards, and monsters all the while living their lives and fulfilling their personal dreams. There have been several video games based on the show.</p><p>The original series had four seasons that aired from 2004 to 2009. In 2011, Viacom (owner of Nickelodeon) became a co-owner of Rainbow SpA, and Viacom launched a revival series. The revival began with four new specials that retell the original first and second seasons.</p>", "games": [{"api_detail_url": "https://www.giantbomb.com/api/game/3030-21154/", "id": 21154, "name": "Winx Club: Mission Enchantix", "site_detail_url": "https://www.giantbomb.com/winx-club-mission-enchantix/3030-21154/"}, {"api_detail_url": "https://www.giantbomb.com/api/game/3030-23614/", "id": 23614, "name": "Winx Club: Quest for the Codex", "site_detail_url": "https://www.giantbomb.com/winx-club-quest-for-the-codex/3030-23614/"}, {"api_detail_url": "https://www.giantbomb.com/api/game/3030-23615/", "id": 23615, "name": "Winx Club", "site_detail_url": "https://www.giantbomb.com/winx-club/3030-23615/"}, {"api_detail_url": "https://www.giantbomb.com/api/game/3030-23616/", "id": 23616, "name": "Winx Club: Join the Club", "site_detail_url": "https://www.giantbomb.com/winx-club-join-the-club/3030-23616/"}, {"api_detail_url": "https://www.giantbomb.com/api/game/3030-39265/", "id": 39265, "name": "Winx Club: Magical Fairy Party", "site_detail_url": "https://www.giantbomb.com/winx-club-magical-fairy-party/3030-39265/"}, {"api_detail_url": "https://www.giantbomb.com/api/game/3030-28031/", "id": 28031, "name": "Winx Club: Believix in You", "site_detail_url": "https://www.giantbomb.com/winx-club-believix-in-you/3030-28031/"}, {"api_detail_url": "https://www.giantbomb.com/api/game/3030-42669/", "id": 42669, "name": "Winx Sirenix Power", "site_detail_url": "https://www.giantbomb.com/winx-sirenix-power/3030-42669/"}, {"api_detail_url": "https://www.giantbomb.com/api/game/3030-47432/", "id": 47432, "name": "Winx Club: Saving Alfea", "site_detail_url": "https://www.giantbomb.com/winx-club-saving-alfea/3030-47432/"}, {"api_detail_url": "https://www.giantbomb.com/api/game/3030-69276/", "id": 69276, "name": "Winx Club: Alfea Butterflix Adventures", "site_detail_url": "https://www.giantbomb.com/winx-club-alfea-butterflix-adventures/3030-69276/"}, {"api_detail_url": "https://www.giantbomb.com/api/game/3030-85829/", "id": 85829, "name": "Winx Club", "site_detail_url": "https://www.giantbomb.com/winx-club/3030-85829/"}], "guid": "3025-1008", "id": 1008, "image": {"icon_url": "https://www.giantbomb.com/a/uploads/square_avatar/11/110502/2288075-winx_club_logo.png", "medium_url": "https://www.giantbomb.com/a/uploads/scale_medium/11/110502/2288075-winx_club_logo.png", "screen_url": "https://www.giantbomb.com/a/uploads/screen_medium/11/110502/2288075-winx_club_logo.png", "screen_large_url": "https://www.giantbomb.com/a/uploads/screen_kubrick/11/110502/2288075-winx_club_logo.png", "small_url": "https://www.giantbomb.com/a/uploads/scale_small/11/110502/2288075-winx_club_logo.png", "super_url": "https://www.giantbomb.com/a/uploads/scale_large/11/110502/2288075-winx_club_logo.png", "thumb_url": "https://www.giantbomb.com/a/uploads/scale_avatar/11/110502/2288075-winx_club_logo.png", "tiny_url": "https://www.giantbomb.com/a/uploads/square_mini/11/110502/2288075-winx_club_logo.png", "original_url": "https://www.giantbomb.com/a/uploads/original/11/110502/2288075-winx_club_logo.png", "image_tags": "All Images,Official Art"}, "image_tags": [{"api_detail_url": "https://www.giantbomb.com/api/images/3025-1008/?filter=image_tag:All%20Images", "name": "All Images", "total": 2}, {"api_detail_url": "https://www.giantbomb.com/api/images/3025-1008/?filter=image_tag:Official%20Art", "name": "Official Art", "total": 2}], "locations": [], "name": "Winx Club", "objects": [{"api_detail_url": "https://www.giantbomb.com/api/object/3055-221/", "id": 221, "name": "Wand", "site_detail_url": "https://www.giantbomb.com/wand/3055-221/"}, {"api_detail_url": "https://www.giantbomb.com/api/object/3055-535/", "id": 535, "name": "Magic Staff", "site_detail_url": "https://www.giantbomb.com/magic-staff/3055-535/"}, {"api_detail_url": "https://www.giantbomb.com/api/object/3055-1971/", "id": 1971, "name": "Wings", "site_detail_url": "https://www.giantbomb.com/wings/3055-1971/"}], "people": [{"api_detail_url": "https://www.giantbomb.com/api/person/3040-99898/", "id": 99898, "name": "Darren Mohle", "site_detail_url": "https://www.giantbomb.com/darren-mohle/3040-99898/"}, {"api_detail_url": "https://www.giantbomb.com/api/person/3040-101612/", "id": 101612, "name": "Anthony Vrakotas", "site_detail_url": "https://www.giantbomb.com/anthony-vrakotas/3040-101612/"}, {"api_detail_url": "https://www.giantbomb.com/api/person/3040-101618/", "id": 101618, "name": "Jody Valdes", "site_detail_url": "https://www.giantbomb.com/jody-valdes/3040-101618/"}, {"api_detail_url": "https://www.giantbomb.com/api/person/3040-102290/", "id": 102290, "name": "Luis Martins", "site_detail_url": "https://www.giantbomb.com/luis-martins/3040-102290/"}, {"api_detail_url": "https://www.giantbomb.com/api/person/3040-102292/", "id": 102292, "name": "Lon Benattar", "site_detail_url": "https://www.giantbomb.com/lon-benattar/3040-102292/"}], "site_detail_url": "https://www.giantbomb.com/winx-club/3025-1008/"}, "version": "1.0"}