{"error": "OK", "limit": 1, "offset": 0, "number_of_page_results": 1, "number_of_total_results": 1, "status_code": 1, "results": {"aliases": null, "api_detail_url": "https://www.giantbomb.com/api/franchise/3025-1027/", "characters": [], "concepts": [{"api_detail_url": "https://www.giantbomb.com/api/concept/3015-39/", "id": 39, "name": "Experience Points", "site_detail_url": "https://www.giantbomb.com/experience-points/3015-39/"}, {"api_detail_url": "https://www.giantbomb.com/api/concept/3015-155/", "id": 155, "name": "Customizable Character", "site_detail_url": "https://www.giantbomb.com/customizable-character/3015-155/"}, {"api_detail_url": "https://www.giantbomb.com/api/concept/3015-125/", "id": 125, "name": "Party System", "site_detail_url": "https://www.giantbomb.com/party-system/3015-125/"}, {"api_detail_url": "https://www.giantbomb.com/api/concept/3015-98/", "id": 98, "name": "Magic", "site_detail_url": "https://www.giantbomb.com/magic/3015-98/"}, {"api_detail_url": "https://www.giantbomb.com/api/concept/3015-161/", "id": 161, "name": "Loot Gathering", "site_detail_url": "https://www.giantbomb.com/loot-gathering/3015-161/"}, {"api_detail_url": "https://www.giantbomb.com/api/concept/3015-399/", "id": 399, "name": "Death Knight", "site_detail_url": "https://www.giantbomb.com/death-knight/3015-399/"}, {"api_detail_url": "https://www.giantbomb.com/api/concept/3015-7565/", "id": 7565, "name": "Player Created Party", "site_detail_url": "https://www.giantbomb.com/player-created-party/3015-7565/"}, {"api_detail_url": "https://www.giantbomb.com/api/concept/3015-405/", "id": 405, "name": "Character Class", "site_detail_url": "https://www.giantbomb.com/character-class/3015-405/"}, {"api_detail_url": "https://www.giantbomb.com/api/concept/3015-7731/", "id": 7731, "name": "Gold Box Engine", "site_detail_url": "https://www.giantbomb.com/gold-box-engine/3015-7731/"}, {"api_detail_url": "https://www.giantbomb.com/api/concept/3015-7750/", "id": 7750, "name": "AD&D Rules", "site_detail_url": "https://www.giantbomb.com/add-rules/3015-7750/"}, {"api_detail_url": "https://www.giantbomb.com/api/concept/3015-475/", "id": 475, "name": "Level Up", "site_detail_url": "https://www.giantbomb.com/level-up/3015-475/"}, {"api_detail_url": "https://www.giantbomb.com/api/concept/3015-4214/", "id": 4214, "name": "One-Dimensionally Evil", "site_detail_url": "https://www.giantbomb.com/one-dimensionally-evil/3015-4214/"}, {"api_detail_url": "https://www.giantbomb.com/api/concept/3015-1694/", "id": 1694, "name": "Wizards", "site_detail_url": "https://www.giantbomb.com/wizards/3015-1694/"}, {"api_detail_url": "https://www.giantbomb.com/api/concept/3015-2648/", "id": 2648, "name": "Fighter", "site_detail_url": "https://www.giantbomb.com/fighter/3015-2648/"}, {"api_detail_url": "https://www.giantbomb.com/api/concept/3015-1460/", "id": 1460, "name": "Rogues", "site_detail_url": "https://www.giantbomb.com/rogues/3015-1460/"}, {"api_detail_url": "https://www.giantbomb.com/api/concept/3015-4055/", "id": 4055, "name": "Clerics", "site_detail_url": "https://www.giantbomb.com/clerics/3015-4055/"}, {"api_detail_url": "https://www.giantbomb.com/api/concept/3015-1318/", "id": 1318, "name": "Grid-Based Movement", "site_detail_url": "https://www.giantbomb.com/grid-based-movement/3015-1318/"}, {"api_detail_url": "https://www.giantbomb.com/api/concept/3015-234/", "id": 234, "name": "Tactical Turn-Based Combat", "site_detail_url": "https://www.giantbomb.com/tactical-turn-based-combat/3015-234/"}, {"api_detail_url": "https://www.giantbomb.com/api/concept/3015-940/", "id": 940, "name": "Dwarf", "site_detail_url": "https://www.giantbomb.com/dwarf/3015-940/"}, {"api_detail_url": "https://www.giantbomb.com/api/concept/3015-537/", "id": 537, "name": "Elf", "site_detail_url": "https://www.giantbomb.com/elf/3015-537/"}, {"api_detail_url": "https://www.giantbomb.com/api/concept/3015-1681/", "id": 1681, "name": "Attributes", "site_detail_url": "https://www.giantbomb.com/attributes/3015-1681/"}, {"api_detail_url": "https://www.giantbomb.com/api/concept/3015-246/", "id": 246, "name": "Isometric Viewpoint", "site_detail_url": "https://www.giantbomb.com/isometric-viewpoint/3015-246/"}, {"api_detail_url": "https://www.giantbomb.com/api/concept/3015-491/", "id": 491, "name": "Sprite", "site_detail_url": "https://www.giantbomb.com/sprite/3015-491/"}, {"api_detail_url": "https://www.giantbomb.com/api/concept/3015-810/", "id": 810, "name": "Human", "site_detail_url": "https://www.giantbomb.com/human/3015-810/"}, {"api_detail_url": "https://www.giantbomb.com/api/concept/3015-1001/", "id": 1001, "name": "In-Game Copyright Protection", "site_detail_url": "https://www.giantbomb.com/in-game-copyright-protection/3015-1001/"}, {"api_detail_url": "https://www.giantbomb.com/api/concept/3015-2854/", "id": 2854, "name": "Rangers", "site_detail_url": "https://www.giantbomb.com/rangers/3015-2854/"}, {"api_detail_url": "https://www.giantbomb.com/api/concept/3015-165/", "id": 165, "name": "Dungeon Crawling", "site_detail_url": "https://www.giantbomb.com/dungeon-crawling/3015-165/"}], "date_added": "2008-09-07 10:05:26", "date_last_updated": "2011-05-05 12:34:21", "deck": "A series of fantasy roleplaying games in the Dragonlance universe using the Dungeons & Dragons ruleset.", "description": null, "games": [{"api_detail_url": "https://www.giantbomb.com/api/game/3030-13987/", "id": 13987, "name": "Champions of Krynn", "site_detail_url": "https://www.giantbomb.com/champions-of-krynn/3030-13987/"}, {"api_detail_url": "https://www.giantbomb.com/api/game/3030-19911/", "id": 19911, "name": "Death Knights of Krynn", "site_detail_url": "https://www.giantbomb.com/death-knights-of-krynn/3030-19911/"}, {"api_detail_url": "https://www.giantbomb.com/api/game/3030-4963/", "id": 4963, "name": "The Dark Queen of Krynn", "site_detail_url": "https://www.giantbomb.com/the-dark-queen-of-krynn/3030-4963/"}], "guid": "3025-1027", "id": 1027, "image": {"icon_url": "https://www.giantbomb.com/a/uploads/square_avatar/1/15693/608548-1919_1_1_.jpg", "medium_url": "https://www.giantbomb.com/a/uploads/scale_medium/1/15693/608548-1919_1_1_.jpg", "screen_url": "https://www.giantbomb.com/a/uploads/screen_medium/1/15693/608548-1919_1_1_.jpg", "screen_large_url": "https://www.giantbomb.com/a/uploads/screen_kubrick/1/15693/608548-1919_1_1_.jpg", "small_url": "https://www.giantbomb.com/a/uploads/scale_small/1/15693/608548-1919_1_1_.jpg", "super_url": "https://www.giantbomb.com/a/uploads/scale_large/1/15693/608548-1919_1_1_.jpg", "thumb_url": "https://www.giantbomb.com/a/uploads/scale_avatar/1/15693/608548-1919_1_1_.jpg", "tiny_url": "https://www.giantbomb.com/a/uploads/square_mini/1/15693/608548-1919_1_1_.jpg", "original_url": "https://www.giantbomb.com/a/uploads/original/1/15693/608548-1919_1_1_.jpg", "image_tags": "All Images,Box Art"}, "image_tags": [{"api_detail_url": "https://www.giantbomb.com/api/images/3025-1027/?filter=image_tag:All%20Images", "name": "All Images", "total": 1}], "locations": [{"api_detail_url": "https://www.giantbomb.com/api/location/3035-3859/", "id": 3859, "name": "Krynn", "site_detail_url": "https://www.giantbomb.com/krynn/3035-3859/"}, {"api_detail_url": "https://www.giantbomb.com/api/location/3035-29/", "id": 29, "name": "The Forgotten Realms", "site_detail_url": "https://www.giantbomb.com/the-forgotten-realms/3035-29/"}], "name": "Krynn", "objects": [{"api_detail_url": "https://www.giantbomb.com/api/object/3055-1/", "id": 1, "name": "Sword", "site_detail_url": "https://www.giantbomb.com/sword/3055-1/"}, {"api_detail_url": "https://www.giantbomb.com/api/object/3055-73/", "id": 73, "name": "Bow", "site_detail_url": "https://www.giantbomb.com/bow/3055-73/"}, {"api_detail_url": "https://www.giantbomb.com/api/object/3055-87/", "id": 87, "name": "Shield", "site_detail_url": "https://www.giantbomb.com/shield/3055-87/"}, {"api_detail_url": "https://www.giantbomb.com/api/object/3055-79/", "id": 79, "name": "Potion", "site_detail_url": "https://www.giantbomb.com/potion/3055-79/"}, {"api_detail_url": "https://www.giantbomb.com/api/object/3055-107/", "id": 107, "name": "Crossbow", "site_detail_url": "https://www.giantbomb.com/crossbow/3055-107/"}, {"api_detail_url": "https://www.giantbomb.com/api/object/3055-787/", "id": 787, "name": "Metal Armor", "site_detail_url": "https://www.giantbomb.com/metal-armor/3055-787/"}, {"api_detail_url": "https://www.giantbomb.com/api/object/3055-83/", "id": 83, "name": "Gold", "site_detail_url": "https://www.giantbomb.com/gold/3055-83/"}, {"api_detail_url": "https://www.giantbomb.com/api/object/3055-1306/", "id": 1306, "name": "Dagger", "site_detail_url": "https://www.giantbomb.com/dagger/3055-1306/"}], "people": [{"api_detail_url": "https://www.giantbomb.com/api/person/3040-11056/", "id": 11056, "name": "Hitoshi Sakimoto", "site_detail_url": "https://www.giantbomb.com/hitoshi-sakimoto/3040-11056/"}, {"api_detail_url": "https://www.giantbomb.com/api/person/3040-2328/", "id": 2328, "name": "Glen A. Cureton", "site_detail_url": "https://www.giantbomb.com/glen-a-cureton/3040-2328/"}, {"api_detail_url": "https://www.giantbomb.com/api/person/3040-4619/", "id": 4619, "name": "Rick E. White", "site_detail_url": "https://www.giantbomb.com/rick-e-white/3040-4619/"}, {"api_detail_url": "https://www.giantbomb.com/api/person/3040-2321/", "id": 2321, "name": "Eileen Matsumi", "site_detail_url": "https://www.giantbomb.com/eileen-matsumi/3040-2321/"}, {"api_detail_url": "https://www.giantbomb.com/api/person/3040-2322/", "id": 2322, "name": "Andr\u00e9 Vrignaud", "site_detail_url": "https://www.giantbomb.com/andre-vrignaud/3040-2322/"}, {"api_detail_url": "https://www.giantbomb.com/api/person/3040-5143/", "id": 5143, "name": "Bret Berry", "site_detail_url": "https://www.giantbomb.com/bret-berry/3040-5143/"}, {"api_detail_url": "https://www.giantbomb.com/api/person/3040-4611/", "id": 4611, "name": "Laura R. Bowen", "site_detail_url": "https://www.giantbomb.com/laura-r-bowen/3040-4611/"}, {"api_detail_url": "https://www.giantbomb.com/api/person/3040-6248/", "id": 6248, "name": "Daniel Colon Jr.", "site_detail_url": "https://www.giantbomb.com/daniel-colon-jr/3040-6248/"}, {"api_detail_url": "https://www.giantbomb.com/api/person/3040-2811/", "id": 2811, "name": "Jason Linhart", "site_detail_url": "https://www.giantbomb.com/jason-linhart/3040-2811/"}, {"api_detail_url": "https://www.giantbomb.com/api/person/3040-12751/", "id": 12751, "name": "Wayne Horgan", "site_detail_url": "https://www.giantbomb.com/wayne-horgan/3040-12751/"}, {"api_detail_url": "https://www.giantbomb.com/api/person/3040-10007/", "id": 10007, "name": "Thomas A. MacMahon", "site_detail_url": "https://www.giantbomb.com/thomas-a-macmahon/3040-10007/"}, {"api_detail_url": "https://www.giantbomb.com/api/person/3040-10009/", "id": 10009, "name": "Tao Rodriguez-Seeger", "site_detail_url": "https://www.giantbomb.com/tao-rodriguez-seeger/3040-10009/"}, {"api_detail_url": "https://www.giantbomb.com/api/person/3040-10006/", "id": 10006, "name": "Bill Sloan", "site_detail_url": "https://www.giantbomb.com/bill-sloan/3040-10006/"}, {"api_detail_url": "https://www.giantbomb.com/api/person/3040-10008/", "id": 10008, "name": "Emma Tailleir", "site_detail_url": "https://www.giantbomb.com/emma-tailleir/3040-10008/"}, {"api_detail_url": "https://www.giantbomb.com/api/person/3040-9992/", "id": 9992, "name": "David Blake", "site_detail_url": "https://www.giantbomb.com/david-blake/3040-9992/"}, {"api_detail_url": "https://www.giantbomb.com/api/person/3040-2805/", "id": 2805, "name": "Kiri Naiman", "site_detail_url": "https://www.giantbomb.com/kiri-naiman/3040-2805/"}, {"api_detail_url": "https://www.giantbomb.com/api/person/3040-2807/", "id": 2807, "name": "Herb Perez", "site_detail_url": "https://www.giantbomb.com/herb-perez/3040-2807/"}, {"api_detail_url": "https://www.giantbomb.com/api/person/3040-2806/", "id": 2806, "name": "Carol Tanguay", "site_detail_url": "https://www.giantbomb.com/carol-tanguay/3040-2806/"}, {"api_detail_url": "https://www.giantbomb.com/api/person/3040-2325/", "id": 2325, "name": "Kym Goyer", "site_detail_url": "https://www.giantbomb.com/kym-goyer/3040-2325/"}, {"api_detail_url": "https://www.giantbomb.com/api/person/3040-4621/", "id": 4621, "name": "James Young", "site_detail_url": "https://www.giantbomb.com/james-young/3040-4621/"}, {"api_detail_url": "https://www.giantbomb.com/api/person/3040-10004/", "id": 10004, "name": "Forrest Elam", "site_detail_url": "https://www.giantbomb.com/forrest-elam/3040-10004/"}, {"api_detail_url": "https://www.giantbomb.com/api/person/3040-2330/", "id": 2330, "name": "Brian Lowe", "site_detail_url": "https://www.giantbomb.com/brian-lowe/3040-2330/"}, {"api_detail_url": "https://www.giantbomb.com/api/person/3040-9061/", "id": 9061, "name": "Clyde Caldwell", "site_detail_url": "https://www.giantbomb.com/clyde-caldwell/3040-9061/"}, {"api_detail_url": "https://www.giantbomb.com/api/person/3040-4598/", "id": 4598, "name": "David Shelley", "site_detail_url": "https://www.giantbomb.com/david-shelley/3040-4598/"}, {"api_detail_url": "https://www.giantbomb.com/api/person/3040-4597/", "id": 4597, "name": "Victor Penman", "site_detail_url": "https://www.giantbomb.com/victor-penman/3040-4597/"}, {"api_detail_url": "https://www.giantbomb.com/api/person/3040-4623/", "id": 4623, "name": "Peter Gascoyne", "site_detail_url": "https://www.giantbomb.com/peter-gascoyne/3040-4623/"}, {"api_detail_url": "https://www.giantbomb.com/api/person/3040-2316/", "id": 2316, "name": "Kirk Nichols", "site_detail_url": "https://www.giantbomb.com/kirk-nichols/3040-2316/"}, {"api_detail_url": "https://www.giantbomb.com/api/person/3040-2804/", "id": 2804, "name": "Stephen Linhart", "site_detail_url": "https://www.giantbomb.com/stephen-linhart/3040-2804/"}, {"api_detail_url": "https://www.giantbomb.com/api/person/3040-2809/", "id": 2809, "name": "Lester Humphreys", "site_detail_url": "https://www.giantbomb.com/lester-humphreys/3040-2809/"}, {"api_detail_url": "https://www.giantbomb.com/api/person/3040-4609/", "id": 4609, "name": "Cyrus Lum", "site_detail_url": "https://www.giantbomb.com/cyrus-lum/3040-4609/"}, {"api_detail_url": "https://www.giantbomb.com/api/person/3040-9989/", "id": 9989, "name": "Michael Provenza", "site_detail_url": "https://www.giantbomb.com/michael-provenza/3040-9989/"}, {"api_detail_url": "https://www.giantbomb.com/api/person/3040-4616/", "id": 4616, "name": "Erik Flom", "site_detail_url": "https://www.giantbomb.com/erik-flom/3040-4616/"}, {"api_detail_url": "https://www.giantbomb.com/api/person/3040-4617/", "id": 4617, "name": "Clifford Mann", "site_detail_url": "https://www.giantbomb.com/clifford-mann/3040-4617/"}, {"api_detail_url": "https://www.giantbomb.com/api/person/3040-4618/", "id": 4618, "name": "Don McClure", "site_detail_url": "https://www.giantbomb.com/don-mcclure/3040-4618/"}, {"api_detail_url": "https://www.giantbomb.com/api/person/3040-4707/", "id": 4707, "name": "Larry Stephen Webber", "site_detail_url": "https://www.giantbomb.com/larry-stephen-webber/3040-4707/"}, {"api_detail_url": "https://www.giantbomb.com/api/person/3040-4620/", "id": 4620, "name": "Richard Wilson", "site_detail_url": "https://www.giantbomb.com/richard-wilson/3040-4620/"}, {"api_detail_url": "https://www.giantbomb.com/api/person/3040-9059/", "id": 9059, "name": "John Kirk", "site_detail_url": "https://www.giantbomb.com/john-kirk/3040-9059/"}, {"api_detail_url": "https://www.giantbomb.com/api/person/3040-2327/", "id": 2327, "name": "John C. Boockholdt", "site_detail_url": "https://www.giantbomb.com/john-c-boockholdt/3040-2327/"}, {"api_detail_url": "https://www.giantbomb.com/api/person/3040-4605/", "id": 4605, "name": "Michael Mancuso", "site_detail_url": "https://www.giantbomb.com/michael-mancuso/3040-4605/"}, {"api_detail_url": "https://www.giantbomb.com/api/person/3040-4604/", "id": 4604, "name": "Ken Humphries", "site_detail_url": "https://www.giantbomb.com/ken-humphries/3040-4604/"}, {"api_detail_url": "https://www.giantbomb.com/api/person/3040-4602/", "id": 4602, "name": "James Jennings", "site_detail_url": "https://www.giantbomb.com/james-jennings/3040-4602/"}, {"api_detail_url": "https://www.giantbomb.com/api/person/3040-2326/", "id": 2326, "name": "Philip L. Alne", "site_detail_url": "https://www.giantbomb.com/philip-l-alne/3040-2326/"}, {"api_detail_url": "https://www.giantbomb.com/api/person/3040-2332/", "id": 2332, "name": "Alan Marenco", "site_detail_url": "https://www.giantbomb.com/alan-marenco/3040-2332/"}, {"api_detail_url": "https://www.giantbomb.com/api/person/3040-9999/", "id": 9999, "name": "Maurine Y. Starkey", "site_detail_url": "https://www.giantbomb.com/maurine-y-starkey/3040-9999/"}, {"api_detail_url": "https://www.giantbomb.com/api/person/3040-6855/", "id": 6855, "name": "Ken Eklund", "site_detail_url": "https://www.giantbomb.com/ken-eklund/3040-6855/"}, {"api_detail_url": "https://www.giantbomb.com/api/person/3040-9996/", "id": 9996, "name": "Gary Shockley", "site_detail_url": "https://www.giantbomb.com/gary-shockley/3040-9996/"}, {"api_detail_url": "https://www.giantbomb.com/api/person/3040-6817/", "id": 6817, "name": "Sean House", "site_detail_url": "https://www.giantbomb.com/sean-house/3040-6817/"}, {"api_detail_url": "https://www.giantbomb.com/api/person/3040-10003/", "id": 10003, "name": "Thomas MacDevitt", "site_detail_url": "https://www.giantbomb.com/thomas-macdevitt/3040-10003/"}, {"api_detail_url": "https://www.giantbomb.com/api/person/3040-2337/", "id": 2337, "name": "Ray Garcia", "site_detail_url": "https://www.giantbomb.com/ray-garcia/3040-2337/"}, {"api_detail_url": "https://www.giantbomb.com/api/person/3040-10010/", "id": 10010, "name": "Zane Wolters", "site_detail_url": "https://www.giantbomb.com/zane-wolters/3040-10010/"}, {"api_detail_url": "https://www.giantbomb.com/api/person/3040-13008/", "id": 13008, "name": "Thomas Heinks", "site_detail_url": "https://www.giantbomb.com/thomas-heinks/3040-13008/"}, {"api_detail_url": "https://www.giantbomb.com/api/person/3040-9770/", "id": 9770, "name": "Jasper Bongertz", "site_detail_url": "https://www.giantbomb.com/jasper-bongertz/3040-9770/"}], "site_detail_url": "https://www.giantbomb.com/krynn/3025-1027/"}, "version": "1.0"}