{"error": "OK", "limit": 1, "offset": 0, "number_of_page_results": 1, "number_of_total_results": 1, "status_code": 1, "results": {"games": [{"api_detail_url": "https://www.giantbomb.com/api/game/3030-20855/", "id": 20855, "name": "Balloon Pop", "site_detail_url": "https://www.giantbomb.com/balloon-pop/3030-20855/"}, {"api_detail_url": "https://www.giantbomb.com/api/game/3030-34932/", "id": 34932, "name": "Balloon Pop 2", "site_detail_url": "https://www.giantbomb.com/balloon-pop-2/3030-34932/"}, {"api_detail_url": "https://www.giantbomb.com/api/game/3030-39921/", "id": 39921, "name": "Balloon Pop Remix", "site_detail_url": "https://www.giantbomb.com/balloon-pop-remix/3030-39921/"}, {"api_detail_url": "https://www.giantbomb.com/api/game/3030-40471/", "id": 40471, "name": "Balloon Pop Festival", "site_detail_url": "https://www.giantbomb.com/balloon-pop-festival/3030-40471/"}, {"api_detail_url": "https://www.giantbomb.com/api/game/3030-40472/", "id": 40472, "name": "Balloon Pop Plus", "site_detail_url": "https://www.giantbomb.com/balloon-pop-plus/3030-40472/"}]}, "version": "1.0"}