{"error": "OK", "limit": 1, "offset": 0, "number_of_page_results": 1, "number_of_total_results": 1, "status_code": 1, "results": {"games": [{"api_detail_url": "https://www.giantbomb.com/api/game/3030-37090/", "id": 37090, "name": "Trio The Punch \u2013 Never Forget Me...", "site_detail_url": "https://www.giantbomb.com/trio-the-punch-never-forget-me/3030-37090/"}, {"api_detail_url": "https://www.giantbomb.com/api/game/3030-15480/", "id": 15480, "name": "Yie Ar Kung-Fu", "site_detail_url": "https://www.giantbomb.com/yie-ar-kung-fu/3030-15480/"}, {"api_detail_url": "https://www.giantbomb.com/api/game/3030-13141/", "id": 13141, "name": "Time Pilot", "site_detail_url": "https://www.giantbomb.com/time-pilot/3030-13141/"}, {"api_detail_url": "https://www.giantbomb.com/api/game/3030-1272/", "id": 1272, "name": "Terra Cresta", "site_detail_url": "https://www.giantbomb.com/terra-cresta/3030-1272/"}, {"api_detail_url": "https://www.giantbomb.com/api/game/3030-34438/", "id": 34438, "name": "Super Volleyball", "site_detail_url": "https://www.giantbomb.com/super-volleyball/3030-34438/"}, {"api_detail_url": "https://www.giantbomb.com/api/game/3030-2032/", "id": 2032, "name": "Aero Fighters", "site_detail_url": "https://www.giantbomb.com/aero-fighters/3030-2032/"}, {"api_detail_url": "https://www.giantbomb.com/api/game/3030-14662/", "id": 14662, "name": "Scramble", "site_detail_url": "https://www.giantbomb.com/scramble/3030-14662/"}, {"api_detail_url": "https://www.giantbomb.com/api/game/3030-40407/", "id": 40407, "name": "Rabbit Punch", "site_detail_url": "https://www.giantbomb.com/rabbit-punch/3030-40407/"}, {"api_detail_url": "https://www.giantbomb.com/api/game/3030-17186/", "id": 17186, "name": "Quarth", "site_detail_url": "https://www.giantbomb.com/quarth/3030-17186/"}, {"api_detail_url": "https://www.giantbomb.com/api/game/3030-17073/", "id": 17073, "name": "Pooyan", "site_detail_url": "https://www.giantbomb.com/pooyan/3030-17073/"}, {"api_detail_url": "https://www.giantbomb.com/api/game/3030-3552/", "id": 3552, "name": "Super Dodge Ball", "site_detail_url": "https://www.giantbomb.com/super-dodge-ball/3030-3552/"}, {"api_detail_url": "https://www.giantbomb.com/api/game/3030-18293/", "id": 18293, "name": "Renegade", "site_detail_url": "https://www.giantbomb.com/renegade/3030-18293/"}, {"api_detail_url": "https://www.giantbomb.com/api/game/3030-7451/", "id": 7451, "name": "Moon Cresta", "site_detail_url": "https://www.giantbomb.com/moon-cresta/3030-7451/"}, {"api_detail_url": "https://www.giantbomb.com/api/game/3030-7250/", "id": 7250, "name": "Karate Champ", "site_detail_url": "https://www.giantbomb.com/karate-champ/3030-7250/"}, {"api_detail_url": "https://www.giantbomb.com/api/game/3030-15334/", "id": 15334, "name": "Crazy Climber", "site_detail_url": "https://www.giantbomb.com/crazy-climber/3030-15334/"}, {"api_detail_url": "https://www.giantbomb.com/api/game/3030-4350/", "id": 4350, "name": "Contra", "site_detail_url": "https://www.giantbomb.com/contra/3030-4350/"}, {"api_detail_url": "https://www.giantbomb.com/api/game/3030-4702/", "id": 4702, "name": "BurgerTime", "site_detail_url": "https://www.giantbomb.com/burgertime/3030-4702/"}, {"api_detail_url": "https://www.giantbomb.com/api/game/3030-22457/", "id": 22457, "name": "Haunted Castle", "site_detail_url": "https://www.giantbomb.com/haunted-castle/3030-22457/"}, {"api_detail_url": "https://www.giantbomb.com/api/game/3030-53756/", "id": 53756, "name": "Thunder Cross", "site_detail_url": "https://www.giantbomb.com/thunder-cross/3030-53756/"}]}, "version": "1.0"}