{"error": "OK", "limit": 1, "offset": 0, "number_of_page_results": 1, "number_of_total_results": 1, "status_code": 1, "results": {"games": [{"api_detail_url": "https://www.giantbomb.com/api/game/3030-6550/", "id": 6550, "name": "Victorious Boxers: Revolution", "site_detail_url": "https://www.giantbomb.com/victorious-boxers-revolution/3030-6550/"}, {"api_detail_url": "https://www.giantbomb.com/api/game/3030-13642/", "id": 13642, "name": "Victorious Boxers 2: Fighting Spirit", "site_detail_url": "https://www.giantbomb.com/victorious-boxers-2-fighting-spirit/3030-13642/"}, {"api_detail_url": "https://www.giantbomb.com/api/game/3030-18949/", "id": 18949, "name": "Victorious Boxers: Ippo's Road to Glory", "site_detail_url": "https://www.giantbomb.com/victorious-boxers-ippos-road-to-glory/3030-18949/"}, {"api_detail_url": "https://www.giantbomb.com/api/game/3030-24742/", "id": 24742, "name": "Hajime no Ippo THE FIGHTING! DS", "site_detail_url": "https://www.giantbomb.com/hajime-no-ippo-the-fighting-ds/3030-24742/"}, {"api_detail_url": "https://www.giantbomb.com/api/game/3030-34475/", "id": 34475, "name": "Hajime no Ippo: The Fighting!", "site_detail_url": "https://www.giantbomb.com/hajime-no-ippo-the-fighting/3030-34475/"}, {"api_detail_url": "https://www.giantbomb.com/api/game/3030-46708/", "id": 46708, "name": "Hajime no Ippo: The Fighting!", "site_detail_url": "https://www.giantbomb.com/hajime-no-ippo-the-fighting/3030-46708/"}, {"api_detail_url": "https://www.giantbomb.com/api/game/3030-46710/", "id": 46710, "name": "Hajime no Ippo: The Fighting! 2: Victorious Road", "site_detail_url": "https://www.giantbomb.com/hajime-no-ippo-the-fighting-2-victorious-road/3030-46710/"}, {"api_detail_url": "https://www.giantbomb.com/api/game/3030-46716/", "id": 46716, "name": "Hajime no Ippo: The Fighting! Portable: Victorious Spirits", "site_detail_url": "https://www.giantbomb.com/hajime-no-ippo-the-fighting-portable-victorious-sp/3030-46716/"}, {"api_detail_url": "https://www.giantbomb.com/api/game/3030-47824/", "id": 47824, "name": "Hajime no Ippo: The Fighting!", "site_detail_url": "https://www.giantbomb.com/hajime-no-ippo-the-fighting/3030-47824/"}]}, "version": "1.0"}