{"error": "OK", "limit": 1, "offset": 0, "number_of_page_results": 1, "number_of_total_results": 1, "status_code": 1, "results": {"games": [{"api_detail_url": "https://www.giantbomb.com/api/game/3030-16805/", "id": 16805, "name": "Disney/Pixar's Finding Nemo", "site_detail_url": "https://www.giantbomb.com/disneypixars-finding-nemo/3030-16805/"}, {"api_detail_url": "https://www.giantbomb.com/api/game/3030-26059/", "id": 26059, "name": "Finding Nemo", "site_detail_url": "https://www.giantbomb.com/finding-nemo/3030-26059/"}, {"api_detail_url": "https://www.giantbomb.com/api/game/3030-6744/", "id": 6744, "name": "Finding Nemo: Escape to the Big Blue", "site_detail_url": "https://www.giantbomb.com/finding-nemo-escape-to-the-big-blue/3030-6744/"}, {"api_detail_url": "https://www.giantbomb.com/api/game/3030-12718/", "id": 12718, "name": "Finding Nemo: Nemo's Underwater World of Fun", "site_detail_url": "https://www.giantbomb.com/finding-nemo-nemos-underwater-world-of-fun/3030-12718/"}, {"api_detail_url": "https://www.giantbomb.com/api/game/3030-21546/", "id": 21546, "name": "Finding Nemo: Nemo's Ocean Discoveries", "site_detail_url": "https://www.giantbomb.com/finding-nemo-nemos-ocean-discoveries/3030-21546/"}, {"api_detail_url": "https://www.giantbomb.com/api/game/3030-45422/", "id": 45422, "name": "Nemo's Reef", "site_detail_url": "https://www.giantbomb.com/nemos-reef/3030-45422/"}, {"api_detail_url": "https://www.giantbomb.com/api/game/3030-71199/", "id": 71199, "name": "Finding Dory: Just Keep Swimming", "site_detail_url": "https://www.giantbomb.com/finding-dory-just-keep-swimming/3030-71199/"}, {"api_detail_url": "https://www.giantbomb.com/api/game/3030-77281/", "id": 77281, "name": "Finding Nemo: The Continuing Adventures", "site_detail_url": "https://www.giantbomb.com/finding-nemo-the-continuing-adventures/3030-77281/"}, {"api_detail_url": "https://www.giantbomb.com/api/game/3030-77282/", "id": 77282, "name": "2 Games in 1: Finding Nemo + Finding Nemo: The Continuing Adventures", "site_detail_url": "https://www.giantbomb.com/2-games-in-1-finding-nemo-finding-nemo-the-continu/3030-77282/"}, {"api_detail_url": "https://www.giantbomb.com/api/game/3030-79723/", "id": 79723, "name": "Finding Dory", "site_detail_url": "https://www.giantbomb.com/finding-dory/3030-79723/"}, {"api_detail_url": "https://www.giantbomb.com/api/game/3030-79728/", "id": 79728, "name": "Pixar Pals", "site_detail_url": "https://www.giantbomb.com/pixar-pals/3030-79728/"}]}, "version": "1.0"}