{"error": "OK", "limit": 1, "offset": 0, "number_of_page_results": 1, "number_of_total_results": 1, "status_code": 1, "results": {"games": [{"api_detail_url": "https://www.giantbomb.com/api/game/3030-2208/", "id": 2208, "name": "Pang", "site_detail_url": "https://www.giantbomb.com/pang/3030-2208/"}, {"api_detail_url": "https://www.giantbomb.com/api/game/3030-32278/", "id": 32278, "name": "Pang! 3", "site_detail_url": "https://www.giantbomb.com/pang-3/3030-32278/"}, {"api_detail_url": "https://www.giantbomb.com/api/game/3030-31921/", "id": 31921, "name": "Pang: Magical Michael", "site_detail_url": "https://www.giantbomb.com/pang-magical-michael/3030-31921/"}, {"api_detail_url": "https://www.giantbomb.com/api/game/3030-5664/", "id": 5664, "name": "Super Buster Bros.", "site_detail_url": "https://www.giantbomb.com/super-buster-bros/3030-5664/"}, {"api_detail_url": "https://www.giantbomb.com/api/game/3030-6211/", "id": 6211, "name": "Buster Bros. Collection", "site_detail_url": "https://www.giantbomb.com/buster-bros-collection/3030-6211/"}, {"api_detail_url": "https://www.giantbomb.com/api/game/3030-41092/", "id": 41092, "name": "Mighty! Pang", "site_detail_url": "https://www.giantbomb.com/mighty-pang/3030-41092/"}, {"api_detail_url": "https://www.giantbomb.com/api/game/3030-41093/", "id": 41093, "name": "Pang Pom's", "site_detail_url": "https://www.giantbomb.com/pang-poms/3030-41093/"}, {"api_detail_url": "https://www.giantbomb.com/api/game/3030-41096/", "id": 41096, "name": "Super Pang II", "site_detail_url": "https://www.giantbomb.com/super-pang-ii/3030-41096/"}, {"api_detail_url": "https://www.giantbomb.com/api/game/3030-50465/", "id": 50465, "name": "Pang Adventures", "site_detail_url": "https://www.giantbomb.com/pang-adventures/3030-50465/"}]}, "version": "1.0"}