{"error": "OK", "limit": 1, "offset": 0, "number_of_page_results": 1, "number_of_total_results": 1, "status_code": 1, "results": {"games": [{"api_detail_url": "https://www.giantbomb.com/api/game/3030-4548/", "id": 4548, "name": "Savage: The Battle for Newerth", "site_detail_url": "https://www.giantbomb.com/savage-the-battle-for-newerth/3030-4548/"}, {"api_detail_url": "https://www.giantbomb.com/api/game/3030-11254/", "id": 11254, "name": "Savage 2: A Tortured Soul", "site_detail_url": "https://www.giantbomb.com/savage-2-a-tortured-soul/3030-11254/"}, {"api_detail_url": "https://www.giantbomb.com/api/game/3030-53946/", "id": 53946, "name": "Savage Resurrection", "site_detail_url": "https://www.giantbomb.com/savage-resurrection/3030-53946/"}]}, "version": "1.0"}