{"error": "OK", "limit": 1, "offset": 0, "number_of_page_results": 1, "number_of_total_results": 1, "status_code": 1, "results": {"games": [{"api_detail_url": "https://www.giantbomb.com/api/game/3030-55021/", "id": 55021, "name": "Space Pirates and Zombies 2", "site_detail_url": "https://www.giantbomb.com/space-pirates-and-zombies-2/3030-55021/"}, {"api_detail_url": "https://www.giantbomb.com/api/game/3030-35942/", "id": 35942, "name": "Space Pirates and Zombies", "site_detail_url": "https://www.giantbomb.com/space-pirates-and-zombies/3030-35942/"}]}, "version": "1.0"}