{"error": "OK", "limit": 1, "offset": 0, "number_of_page_results": 1, "number_of_total_results": 1, "status_code": 1, "results": {"games": [{"api_detail_url": "https://www.giantbomb.com/api/game/3030-738/", "id": 738, "name": "Black & White 2: Battle of the Gods", "site_detail_url": "https://www.giantbomb.com/black-white-2-battle-of-the-gods/3030-738/"}, {"api_detail_url": "https://www.giantbomb.com/api/game/3030-12474/", "id": 12474, "name": "Black & White 2", "site_detail_url": "https://www.giantbomb.com/black-white-2/3030-12474/"}, {"api_detail_url": "https://www.giantbomb.com/api/game/3030-14823/", "id": 14823, "name": "Black & White: Creature Isle", "site_detail_url": "https://www.giantbomb.com/black-white-creature-isle/3030-14823/"}, {"api_detail_url": "https://www.giantbomb.com/api/game/3030-18623/", "id": 18623, "name": "Black & White", "site_detail_url": "https://www.giantbomb.com/black-white/3030-18623/"}]}, "version": "1.0"}