{"error": "OK", "limit": 1, "offset": 0, "number_of_page_results": 1, "number_of_total_results": 1, "status_code": 1, "results": {"games": [{"api_detail_url": "https://www.giantbomb.com/api/game/3030-44180/", "id": 44180, "name": "Angry Fish: Halloween", "site_detail_url": "https://www.giantbomb.com/angry-fish-halloween/3030-44180/"}, {"api_detail_url": "https://www.giantbomb.com/api/game/3030-38344/", "id": 38344, "name": "Angry Fish", "site_detail_url": "https://www.giantbomb.com/angry-fish/3030-38344/"}, {"api_detail_url": "https://www.giantbomb.com/api/game/3030-44181/", "id": 44181, "name": "Angry Fish: Deep Sea", "site_detail_url": "https://www.giantbomb.com/angry-fish-deep-sea/3030-44181/"}]}, "version": "1.0"}